FIS_labextension/__init__.py
FIS_labextension/_version.py
fis_labextension-0.1.0.data/data/share/jupyter/labextensions/FIS_labextension/build_log.json
fis_labextension-0.1.0.data/data/share/jupyter/labextensions/FIS_labextension/package.json
fis_labextension-0.1.0.data/data/share/jupyter/labextensions/FIS_labextension/static/lib_index_js.e7d8ec9f1176dd3c3964.js
fis_labextension-0.1.0.data/data/share/jupyter/labextensions/FIS_labextension/static/lib_index_js.e7d8ec9f1176dd3c3964.js.map
fis_labextension-0.1.0.data/data/share/jupyter/labextensions/FIS_labextension/static/remoteEntry.3e3f5691172d67792481.js
fis_labextension-0.1.0.data/data/share/jupyter/labextensions/FIS_labextension/static/remoteEntry.3e3f5691172d67792481.js.map
fis_labextension-0.1.0.data/data/share/jupyter/labextensions/FIS_labextension/static/style.js
fis_labextension-0.1.0.data/data/share/jupyter/labextensions/FIS_labextension/static/style_index_js.3aa613ec3d95a15885c0.js
fis_labextension-0.1.0.data/data/share/jupyter/labextensions/FIS_labextension/static/style_index_js.3aa613ec3d95a15885c0.js.map
fis_labextension-0.1.0.data/data/share/jupyter/labextensions/FIS_labextension/install.json
fis_labextension-0.1.0.dist-info/METADATA
fis_labextension-0.1.0.dist-info/WHEEL
fis_labextension-0.1.0.dist-info/licenses/LICENSE
fis_labextension-0.1.0.dist-info/RECORD
