Metadata-Version: 2.1
Name: FIS_labextension
Version: 0.1.0
Summary: A JupyterLab extension.
Project-URL: Homepage, https://github.com/KhajaMuheeb/FIS_CodeAssiatant.git
Project-URL: Bug Tracker, https://github.com/KhajaMuheeb/FIS_CodeAssiatant.git/issues
Project-URL: Repository, https://github.com/KhajaMuheeb/FIS_CodeAssiatant.git.git
Author-email: KhajaMuheeb <khaja.muheeb@fisclouds.com>
License: BSD 3-Clause License
License-File: LICENSE
Classifier: Framework :: Jupyter
Classifier: Framework :: Jupyter :: JupyterLab
Classifier: Framework :: Jupyter :: JupyterLab :: 4
Classifier: Framework :: Jupyter :: JupyterLab :: Extensions
Classifier: Framework :: Jupyter :: JupyterLab :: Extensions :: Prebuilt
Classifier: License :: OSI Approved :: BSD License
Classifier: Programming Language :: Python
Classifier: Programming Language :: Python :: 3
Classifier: Programming Language :: Python :: 3.8
Classifier: Programming Language :: Python :: 3.9
Classifier: Programming Language :: Python :: 3.10
Classifier: Programming Language :: Python :: 3.11
Classifier: Programming Language :: Python :: 3.12
Requires-Python: >=3.8
